python_dropbox_api/__init__.py
python_dropbox_api/auth.py
python_dropbox_api/client.py
python_dropbox_api/exceptions.py
python_dropbox_api/models.py
python_dropbox_api/py.typed
python_dropbox_api-0.1.1.dist-info/METADATA
python_dropbox_api-0.1.1.dist-info/WHEEL
python_dropbox_api-0.1.1.dist-info/RECORD
