Metadata-Version: 2.4
Name: python-dropbox-api
Version: 0.1.1
Summary: 
Author: Brandon Rothweiler
Author-email: 2292715+bdr99@users.noreply.github.com
Requires-Python: >=3.13
Classifier: Programming Language :: Python :: 3
Classifier: Programming Language :: Python :: 3.13
Classifier: Programming Language :: Python :: 3.14
Requires-Dist: aiohttp (>=3.13.0,<4.0.0)
